onlineafspraken/__init__.py
onlineafspraken/onlineafspraken.py
onlineafspraken/api/__init__.py
onlineafspraken/api/appointment.py
onlineafspraken/api/availability.py
onlineafspraken/api/client.py
onlineafspraken/api/customers.py
onlineafspraken/api/general.py
onlineafspraken/api/utils.py
onlineafspraken/schema/__init__.py
onlineafspraken/schema/appointment.py
onlineafspraken/schema/availability.py
onlineafspraken/schema/customer.py
onlineafspraken/schema/general.py
onlineafspraken/schema/response.py
onlineafspraken-0.2.8.dist-info/LICENSE
onlineafspraken-0.2.8.dist-info/METADATA
onlineafspraken-0.2.8.dist-info/WHEEL
onlineafspraken-0.2.8.dist-info/top_level.txt
onlineafspraken-0.2.8.dist-info/RECORD
