Metadata-Version: 2.1
Name: onlineafspraken
Version: 0.2.8
Summary: API client for onlineafspraken.nl
Home-page: https://github.com/HosniD/onlineafspraken
Author: Hosni Dahmani
Author-email: hosni@hellotanit.com
License: MIT license
Keywords: onlineafspraken
Platform: UNKNOWN
Classifier: Development Status :: 2 - Pre-Alpha
Classifier: Intended Audience :: Developers
Classifier: License :: OSI Approved :: MIT License
Classifier: Natural Language :: English
Classifier: Programming Language :: Python :: 3
Classifier: Programming Language :: Python :: 3.6
Classifier: Programming Language :: Python :: 3.7
Classifier: Programming Language :: Python :: 3.8
Requires-Python: >=3.6
License-File: LICENSE
Requires-Dist: python-decouple
Requires-Dist: xmltodict
Requires-Dist: pydantic
Requires-Dist: respx
Requires-Dist: httpx
